modelfacts/__init__.py
modelfacts/examples/__init__.py
modelfacts/examples/preprocess.py
modelfacts/modelfacts/__init__.py
modelfacts/modelfacts/mfl.py
modelfacts/modelfacts/mfw.py
modelfacts-0.0.3.dist-info/METADATA
modelfacts-0.0.3.dist-info/WHEEL
modelfacts-0.0.3.dist-info/licenses/LICENSE
modelfacts-0.0.3.dist-info/RECORD
