Metadata-Version: 2.4
Name: ModelFacts
Version: 0.0.3
Summary: Generate Model Facts Label for AI/ML trust and transparency
Project-URL: Homepage, https://github.com/jhzsquared/model_facts
Project-URL: Issues, https://github.com/jhzsquared/model_facts/issues
Author-email: Jessica Zhu <jhzsquared@gmail.com>
License-Expression: MIT
License-File: LICENSE
Classifier: Intended Audience :: Developers
Classifier: Intended Audience :: End Users/Desktop
Classifier: Intended Audience :: Healthcare Industry
Classifier: Intended Audience :: Science/Research
Classifier: Operating System :: OS Independent
Classifier: Programming Language :: Python :: 3
Requires-Python: >=3.8
Requires-Dist: great-tables>=0.16.1
Requires-Dist: ipywidgets>=8.1.5
Requires-Dist: jupyter
Requires-Dist: notebook
Requires-Dist: numpy>=2.2.3
Requires-Dist: pandas>=2.2.3
Requires-Dist: scikit-learn>=1.6.1
